bmc/__init__.py
bmc/_bmc.so
bmc/bmc.py
kbench/__init__.py
kbench/classes/__init__.py
kbench/classes/cred3.py
kbench/classes/deformable_mirror.py
kbench/classes/filter_wheel.py
kbench/classes/photonic_chip.py
kbench/classes/pupil_mask.py
kbench/modules/__init__.py
kbench/modules/atmosphere.py
kbench/sandbox/__init__.py
kbench/sandbox/bmc_mock.py
kbench/sandbox/serial_mock.py
kbench/sandbox/xaosim_mock.py
kbench/scripts/__init__.py
kbench/scripts/cli.py
kbench/scripts/N4x4_T8/characterize.py
phobos/__init__.py
phobos/classes/__init__.py
phobos/classes/cred3.py
phobos/classes/deformable_mirror.py
phobos/classes/filter_wheel.py
phobos/classes/photonic_chip.py
phobos/classes/pupil_mask.py
phobos/modules/__init__.py
phobos/modules/atmosphere.py
phobos/sandbox/__init__.py
phobos/sandbox/bmc_mock.py
phobos/sandbox/serial_mock.py
phobos/sandbox/xaosim_mock.py
phobos/scripts/__init__.py
phobos/scripts/cli.py
phobos/scripts/N4x4_T8/characterize.py
phob-0.8.0.dist-info/METADATA
phob-0.8.0.dist-info/WHEEL
phob-0.8.0.dist-info/entry_points.txt
phob-0.8.0.dist-info/top_level.txt
phob-0.8.0.dist-info/RECORD
