Metadata-Version: 2.4
Name: phob
Version: 0.8.0
Summary: Python package for controlling optical test bench equipment in kernel-nulling interferometry
Author-email: Vincent Foriel <vincent.foriel@gmail.com>, mmartinod <ma.martinod@free.fr>
License: MIT
Classifier: Development Status :: 4 - Beta
Classifier: Intended Audience :: Science/Research
Classifier: License :: OSI Approved :: MIT License
Classifier: Programming Language :: Python :: 3
Classifier: Programming Language :: Python :: 3.12
Classifier: Topic :: Scientific/Engineering :: Physics
Requires-Python: >=3.12
Requires-Dist: numpy
Requires-Dist: pyserial
Requires-Dist: pyyaml
Requires-Dist: toml>=0.10.2
